jupyter_earth/__init__.py
jupyter_earth/_version.py
jupyter_earth/handlers.py
jupyter_earth/tests/__init__.py
jupyter_earth/tests/test_handlers.py
jupyter_earth-0.0.2.data/data/etc/jupyter/jupyter_notebook_config.d/jupyter_earth.json
jupyter_earth-0.0.2.data/data/etc/jupyter/jupyter_server_config.d/jupyter_earth.json
jupyter_earth-0.0.2.data/data/share/jupyter/labextensions/@datalayer/jupyter-earth/build_log.json
jupyter_earth-0.0.2.data/data/share/jupyter/labextensions/@datalayer/jupyter-earth/package.json
jupyter_earth-0.0.2.data/data/share/jupyter/labextensions/@datalayer/jupyter-earth/schemas/@datalayer/jupyter-earth/package.json.orig
jupyter_earth-0.0.2.data/data/share/jupyter/labextensions/@datalayer/jupyter-earth/schemas/@datalayer/jupyter-earth/plugin.json
jupyter_earth-0.0.2.data/data/share/jupyter/labextensions/@datalayer/jupyter-earth/static/lib_index_js.16a3a1d5796dc4bd8645.js
jupyter_earth-0.0.2.data/data/share/jupyter/labextensions/@datalayer/jupyter-earth/static/lib_index_js.16a3a1d5796dc4bd8645.js.map
jupyter_earth-0.0.2.data/data/share/jupyter/labextensions/@datalayer/jupyter-earth/static/remoteEntry.63ad14849372b59ab7a7.js
jupyter_earth-0.0.2.data/data/share/jupyter/labextensions/@datalayer/jupyter-earth/static/remoteEntry.63ad14849372b59ab7a7.js.map
jupyter_earth-0.0.2.data/data/share/jupyter/labextensions/@datalayer/jupyter-earth/static/style.js
jupyter_earth-0.0.2.data/data/share/jupyter/labextensions/@datalayer/jupyter-earth/static/style_index_js.6799587b7732f19f4a1f.js
jupyter_earth-0.0.2.data/data/share/jupyter/labextensions/@datalayer/jupyter-earth/static/style_index_js.6799587b7732f19f4a1f.js.map
jupyter_earth-0.0.2.data/data/share/jupyter/labextensions/@datalayer/jupyter-earth/static/vendors-node_modules_css-loader_dist_runtime_api_js-node_modules_css-loader_dist_runtime_cssW-72eba1.f1499fe11dfeb832409c.js
jupyter_earth-0.0.2.dist-info/METADATA
jupyter_earth-0.0.2.dist-info/WHEEL
jupyter_earth-0.0.2.dist-info/licenses/LICENSE
jupyter_earth-0.0.2.dist-info/RECORD
